{
  "update_time": "2026-05-16 18:57:40",
  "etf_count": 12,
  "data": [
    {
      "etf_code": "00981A",
      "etf_name": "主動統一台股增長",
      "price": 28.42,
      "change": -1.02,
      "change_pct": -3.46,
      "trade_value": 13377206130,
      "trade_value_billion": 133.77,
      "trade_volume": 462469869,
      "trade_volume_lots": 462469,
      "high": 29.85,
      "low": 28.33,
      "aum": 257186000000.0,
      "aum_billion": 2571.86,
      "aum_date": "2026/05/16"
    },
    {
      "etf_code": "00403A",
      "etf_name": "主動統一升級50",
      "price": 10.0,
      "change": -0.24,
      "change_pct": -2.34,
      "trade_value": 18747747711,
      "trade_value_billion": 187.48,
      "trade_volume": 1856314715,
      "trade_volume_lots": 1856314,
      "high": 10.38,
      "low": 10.0,
      "aum": 146994000000.0,
      "aum_billion": 1469.94,
      "aum_date": "2026/05/16"
    },
    {
      "etf_code": "00992A",
      "etf_name": "主動群益科技創新",
      "price": 17.42,
      "change": -0.82,
      "change_pct": -4.5,
      "trade_value": 2771651491,
      "trade_value_billion": 27.72,
      "trade_volume": 155930845,
      "trade_volume_lots": 155930,
      "high": 18.43,
      "low": 17.38,
      "aum": 49717000000.0,
      "aum_billion": 497.17,
      "aum_date": "2026/05/16"
    },
    {
      "etf_code": "00982A",
      "etf_name": "主動群益台灣強棒",
      "price": 22.55,
      "change": -0.6,
      "change_pct": -2.59,
      "trade_value": 3073498031,
      "trade_value_billion": 30.73,
      "trade_volume": 134337648,
      "trade_volume_lots": 134337,
      "high": 23.45,
      "low": 22.5,
      "aum": 48083000000.0,
      "aum_billion": 480.83,
      "aum_date": "2026/05/16"
    },
    {
      "etf_code": "00991A",
      "etf_name": "主動復華未來50",
      "price": 17.65,
      "change": -0.9,
      "change_pct": -4.85,
      "trade_value": 4372669540,
      "trade_value_billion": 43.73,
      "trade_volume": 242099228,
      "trade_volume_lots": 242099,
      "high": 18.9,
      "low": 17.65,
      "aum": 43244000000.0,
      "aum_billion": 432.44,
      "aum_date": "2026/05/16"
    },
    {
      "etf_code": "00980A",
      "etf_name": "主動野村臺灣優選",
      "price": 23.07,
      "change": -0.95,
      "change_pct": -3.96,
      "trade_value": 857714063,
      "trade_value_billion": 8.58,
      "trade_volume": 36453240,
      "trade_volume_lots": 36453,
      "high": 24.21,
      "low": 23.03,
      "aum": 16623000000.0,
      "aum_billion": 166.23,
      "aum_date": "2026/05/16"
    },
    {
      "etf_code": "00993A",
      "etf_name": "主動安聯台灣",
      "price": 12.66,
      "change": -0.56,
      "change_pct": -4.24,
      "trade_value": 307683816,
      "trade_value_billion": 3.08,
      "trade_volume": 23759898,
      "trade_volume_lots": 23759,
      "high": 13.37,
      "low": 12.66,
      "aum": 11299000000.0,
      "aum_billion": 112.99,
      "aum_date": "2026/05/16"
    },
    {
      "etf_code": "00985A",
      "etf_name": "主動野村台灣50",
      "price": 20.91,
      "change": -0.5,
      "change_pct": -2.34,
      "trade_value": 235227489,
      "trade_value_billion": 2.35,
      "trade_volume": 11109740,
      "trade_volume_lots": 11109,
      "high": 21.66,
      "low": 20.89,
      "aum": 10910000000.0,
      "aum_billion": 109.1,
      "aum_date": "2026/05/16"
    },
    {
      "etf_code": "00984A",
      "etf_name": "主動安聯台灣高息",
      "price": 14.72,
      "change": -0.33,
      "change_pct": -2.19,
      "trade_value": 184207548,
      "trade_value_billion": 1.84,
      "trade_volume": 12359511,
      "trade_volume_lots": 12359,
      "high": 15.15,
      "low": 14.7,
      "aum": 6851000000.0,
      "aum_billion": 68.51,
      "aum_date": "2026/05/16"
    },
    {
      "etf_code": "00994A",
      "etf_name": "主動第一金台股優",
      "price": 16.93,
      "change": -0.77,
      "change_pct": -4.35,
      "trade_value": 324049797,
      "trade_value_billion": 3.24,
      "trade_volume": 18745855,
      "trade_volume_lots": 18745,
      "high": 17.86,
      "low": 16.92,
      "aum": 5371000000.0,
      "aum_billion": 53.71,
      "aum_date": "2026/05/16"
    },
    {
      "etf_code": "00995A",
      "etf_name": "主動中信台灣卓越",
      "price": 16.33,
      "change": -0.73,
      "change_pct": -4.28,
      "trade_value": 223063125,
      "trade_value_billion": 2.23,
      "trade_volume": 13384197,
      "trade_volume_lots": 13384,
      "high": 17.32,
      "low": 16.26,
      "aum": 5344000000.0,
      "aum_billion": 53.44,
      "aum_date": "2026/05/16"
    },
    {
      "etf_code": "00987A",
      "etf_name": "主動台新優勢成長",
      "price": 16.5,
      "change": -0.74,
      "change_pct": -4.29,
      "trade_value": 192906377,
      "trade_value_billion": 1.93,
      "trade_volume": 11416060,
      "trade_volume_lots": 11416,
      "high": 17.38,
      "low": 16.47,
      "aum": 3319000000.0,
      "aum_billion": 33.19,
      "aum_date": "2026/05/16"
    }
  ]
}